OpenSeesPyAssistant/AnalysisAndPostProcessing.py
OpenSeesPyAssistant/Connections.py
OpenSeesPyAssistant/Constants.py
OpenSeesPyAssistant/DataManagement.py
OpenSeesPyAssistant/ErrorHandling.py
OpenSeesPyAssistant/Fibers.py
OpenSeesPyAssistant/FunctionalFeatures.py
OpenSeesPyAssistant/GeometryTemplate.py
OpenSeesPyAssistant/MaterialModels.py
OpenSeesPyAssistant/MemberModel.py
OpenSeesPyAssistant/Section.py
OpenSeesPyAssistant/UVC_calibrated_parameters.txt
OpenSeesPyAssistant/Units.py
OpenSeesPyAssistant/__init__.py
OpenSeesPyAssistant-1.11.dist-info/LICENSE
OpenSeesPyAssistant-1.11.dist-info/METADATA
OpenSeesPyAssistant-1.11.dist-info/WHEEL
OpenSeesPyAssistant-1.11.dist-info/top_level.txt
OpenSeesPyAssistant-1.11.dist-info/RECORD
