Metadata-Version: 2.1
Name: OpenSeesPyAssistant
Version: 1.11
Summary: Python-based Simulation Tools for OpenSeesPy.
Home-page: https://github.com/DonCammne/OpenSeesPyAssistant
Author: Carmine Schipani
Author-email: schipanicarmine96@gmail.com
License: UNKNOWN
Platform: UNKNOWN
Classifier: Programming Language :: Python :: 3
Classifier: License :: OSI Approved :: MIT License
Classifier: Operating System :: OS Independent
Requires-Python: >=3.8
License-File: LICENSE
